adafruit_pyoa.py
adafruit_circuitpython_pyoa-2.6.6.dist-info/licenses/LICENSE
adafruit_circuitpython_pyoa-2.6.6.dist-info/METADATA
adafruit_circuitpython_pyoa-2.6.6.dist-info/WHEEL
adafruit_circuitpython_pyoa-2.6.6.dist-info/top_level.txt
adafruit_circuitpython_pyoa-2.6.6.dist-info/RECORD
