Metadata-Version: 2.4
Name: adafruit-circuitpython-PYOA
Version: 2.6.6
Summary: Python your own Adventure - card & button game
Author-email: Adafruit Industries <circuitpython@adafruit.com>
License: MIT
Project-URL: Homepage, https://github.com/adafruit/Adafruit_CircuitPython_PYOA
Keywords: adafruit,pyoa,text,adventure,hardware,micropython,circuitpython
Classifier: Intended Audience :: Developers
Classifier: Topic :: Software Development :: Libraries
Classifier: Topic :: Software Development :: Embedded Systems
Classifier: Topic :: System :: Hardware
Classifier: License :: OSI Approved :: MIT License
Classifier: Programming Language :: Python :: 3
License-File: LICENSE
Requires-Dist: Adafruit-Blinka
Requires-Dist: adafruit-blinka-displayio
Requires-Dist: adafruit-circuitpython-bitmap-font
Requires-Dist: adafruit-circuitpython-display-button
Requires-Dist: adafruit-circuitpython-touchscreen
Requires-Dist: adafruit-circuitpython-display-text
Requires-Dist: adafruit-circuitpython-cursorcontrol
Provides-Extra: optional
Dynamic: license-file
